{"nodes": [{"id": "unpickler", "label": "unpickler.py", "file_type": "code", "source_file": "graphify-env/lib/python3.14/site-packages/jsonpickle/unpickler.py", "source_location": "L1"}, {"id": "unpickler_decode", "label": "decode()", "file_type": "code", "source_file": "graphify-env/lib/python3.14/site-packages/jsonpickle/unpickler.py", "source_location": "L15"}, {"id": "unpickler_safe_hasattr", "label": "_safe_hasattr()", "file_type": "code", "source_file": "graphify-env/lib/python3.14/site-packages/jsonpickle/unpickler.py", "source_location": "L106"}, {"id": "unpickler_is_json_key", "label": "_is_json_key()", "file_type": "code", "source_file": "graphify-env/lib/python3.14/site-packages/jsonpickle/unpickler.py", "source_location": "L115"}, {"id": "unpickler_proxy", "label": "_Proxy", "file_type": "code", "source_file": "graphify-env/lib/python3.14/site-packages/jsonpickle/unpickler.py", "source_location": "L120"}, {"id": "unpickler_proxy_init", "label": ".__init__()", "file_type": "code", "source_file": "graphify-env/lib/python3.14/site-packages/jsonpickle/unpickler.py", "source_location": "L149"}, {"id": "unpickler_proxy_get", "label": ".get()", "file_type": "code", "source_file": "graphify-env/lib/python3.14/site-packages/jsonpickle/unpickler.py", "source_location": "L152"}, {"id": "unpickler_proxy_reset", "label": ".reset()", "file_type": "code", "source_file": "graphify-env/lib/python3.14/site-packages/jsonpickle/unpickler.py", "source_location": "L155"}, {"id": "unpickler_idproxy", "label": "_IDProxy", "file_type": "code", "source_file": "graphify-env/lib/python3.14/site-packages/jsonpickle/unpickler.py", "source_location": "L159"}, {"id": "unpickler_idproxy_init", "label": ".__init__()", "file_type": "code", "source_file": "graphify-env/lib/python3.14/site-packages/jsonpickle/unpickler.py", "source_location": "L160"}, {"id": "unpickler_idproxy_get", "label": ".get()", "file_type": "code", "source_file": "graphify-env/lib/python3.14/site-packages/jsonpickle/unpickler.py", "source_location": "L164"}, {"id": "unpickler_obj_setattr", "label": "_obj_setattr()", "file_type": "code", "source_file": "graphify-env/lib/python3.14/site-packages/jsonpickle/unpickler.py", "source_location": "L171"}, {"id": "unpickler_obj_setvalue", "label": "_obj_setvalue()", "file_type": "code", "source_file": "graphify-env/lib/python3.14/site-packages/jsonpickle/unpickler.py", "source_location": "L176"}, {"id": "unpickler_loadclass", "label": "loadclass()", "file_type": "code", "source_file": "graphify-env/lib/python3.14/site-packages/jsonpickle/unpickler.py", "source_location": "L181"}, {"id": "unpickler_has_tag", "label": "has_tag()", "file_type": "code", "source_file": "graphify-env/lib/python3.14/site-packages/jsonpickle/unpickler.py", "source_location": "L225"}, {"id": "unpickler_getargs", "label": "getargs()", "file_type": "code", "source_file": "graphify-env/lib/python3.14/site-packages/jsonpickle/unpickler.py", "source_location": "L242"}, {"id": "unpickler_trivialclassic", "label": "_trivialclassic", "file_type": "code", "source_file": "graphify-env/lib/python3.14/site-packages/jsonpickle/unpickler.py", "source_location": "L268"}, {"id": "unpickler_make_blank_classic", "label": "make_blank_classic()", "file_type": "code", "source_file": "graphify-env/lib/python3.14/site-packages/jsonpickle/unpickler.py", "source_location": "L274"}, {"id": "unpickler_loadrepr", "label": "loadrepr()", "file_type": "code", "source_file": "graphify-env/lib/python3.14/site-packages/jsonpickle/unpickler.py", "source_location": "L285"}, {"id": "unpickler_loadmodule", "label": "_loadmodule()", "file_type": "code", "source_file": "graphify-env/lib/python3.14/site-packages/jsonpickle/unpickler.py", "source_location": "L307"}, {"id": "unpickler_has_tag_dict", "label": "has_tag_dict()", "file_type": "code", "source_file": "graphify-env/lib/python3.14/site-packages/jsonpickle/unpickler.py", "source_location": "L332"}, {"id": "unpickler_passthrough", "label": "_passthrough()", "file_type": "code", "source_file": "graphify-env/lib/python3.14/site-packages/jsonpickle/unpickler.py", "source_location": "L349"}, {"id": "unpickler_unpickler", "label": "Unpickler", "file_type": "code", "source_file": "graphify-env/lib/python3.14/site-packages/jsonpickle/unpickler.py", "source_location": "L354"}, {"id": "unpickler_unpickler_init", "label": ".__init__()", "file_type": "code", "source_file": "graphify-env/lib/python3.14/site-packages/jsonpickle/unpickler.py", "source_location": "L355"}, {"id": "unpickler_unpickler_reset", "label": ".reset()", "file_type": "code", "source_file": "graphify-env/lib/python3.14/site-packages/jsonpickle/unpickler.py", "source_location": "L373"}, {"id": "unpickler_unpickler_swap_proxies", "label": "._swap_proxies()", "file_type": "code", "source_file": "graphify-env/lib/python3.14/site-packages/jsonpickle/unpickler.py", "source_location": "L389"}, {"id": "unpickler_unpickler_restore", "label": "._restore()", "file_type": "code", "source_file": "graphify-env/lib/python3.14/site-packages/jsonpickle/unpickler.py", "source_location": "L395"}, {"id": "unpickler_unpickler_register_classes", "label": ".register_classes()", "file_type": "code", "source_file": "graphify-env/lib/python3.14/site-packages/jsonpickle/unpickler.py", "source_location": "L425"}, {"id": "unpickler_unpickler_restore_base64", "label": "._restore_base64()", "file_type": "code", "source_file": "graphify-env/lib/python3.14/site-packages/jsonpickle/unpickler.py", "source_location": "L445"}, {"id": "unpickler_unpickler_restore_base85", "label": "._restore_base85()", "file_type": "code", "source_file": "graphify-env/lib/python3.14/site-packages/jsonpickle/unpickler.py", "source_location": "L451"}, {"id": "unpickler_unpickler_refname", "label": "._refname()", "file_type": "code", "source_file": "graphify-env/lib/python3.14/site-packages/jsonpickle/unpickler.py", "source_location": "L457"}, {"id": "unpickler_unpickler_mkref", "label": "._mkref()", "file_type": "code", "source_file": "graphify-env/lib/python3.14/site-packages/jsonpickle/unpickler.py", "source_location": "L481"}, {"id": "unpickler_unpickler_restore_list", "label": "._restore_list()", "file_type": "code", "source_file": "graphify-env/lib/python3.14/site-packages/jsonpickle/unpickler.py", "source_location": "L493"}, {"id": "unpickler_unpickler_restore_iterator", "label": "._restore_iterator()", "file_type": "code", "source_file": "graphify-env/lib/python3.14/site-packages/jsonpickle/unpickler.py", "source_location": "L507"}, {"id": "unpickler_unpickler_swapref", "label": "._swapref()", "file_type": "code", "source_file": "graphify-env/lib/python3.14/site-packages/jsonpickle/unpickler.py", "source_location": "L513"}, {"id": "unpickler_unpickler_restore_reduce", "label": "._restore_reduce()", "file_type": "code", "source_file": "graphify-env/lib/python3.14/site-packages/jsonpickle/unpickler.py", "source_location": "L524"}, {"id": "unpickler_unpickler_restore_id", "label": "._restore_id()", "file_type": "code", "source_file": "graphify-env/lib/python3.14/site-packages/jsonpickle/unpickler.py", "source_location": "L598"}, {"id": "unpickler_unpickler_restore_type", "label": "._restore_type()", "file_type": "code", "source_file": "graphify-env/lib/python3.14/site-packages/jsonpickle/unpickler.py", "source_location": "L607"}, {"id": "unpickler_unpickler_restore_module", "label": "._restore_module()", "file_type": "code", "source_file": "graphify-env/lib/python3.14/site-packages/jsonpickle/unpickler.py", "source_location": "L613"}, {"id": "unpickler_unpickler_restore_repr_safe", "label": "._restore_repr_safe()", "file_type": "code", "source_file": "graphify-env/lib/python3.14/site-packages/jsonpickle/unpickler.py", "source_location": "L617"}, {"id": "unpickler_unpickler_restore_repr", "label": "._restore_repr()", "file_type": "code", "source_file": "graphify-env/lib/python3.14/site-packages/jsonpickle/unpickler.py", "source_location": "L621"}, {"id": "unpickler_unpickler_loadfactory", "label": "._loadfactory()", "file_type": "code", "source_file": "graphify-env/lib/python3.14/site-packages/jsonpickle/unpickler.py", "source_location": "L625"}, {"id": "unpickler_unpickler_process_missing", "label": "._process_missing()", "file_type": "code", "source_file": "graphify-env/lib/python3.14/site-packages/jsonpickle/unpickler.py", "source_location": "L633"}, {"id": "unpickler_unpickler_restore_pickled_key", "label": "._restore_pickled_key()", "file_type": "code", "source_file": "graphify-env/lib/python3.14/site-packages/jsonpickle/unpickler.py", "source_location": "L646"}, {"id": "unpickler_unpickler_restore_key_fn", "label": "._restore_key_fn()", "file_type": "code", "source_file": "graphify-env/lib/python3.14/site-packages/jsonpickle/unpickler.py", "source_location": "L658"}, {"id": "unpickler_unpickler_restore_from_dict", "label": "._restore_from_dict()", "file_type": "code", "source_file": "graphify-env/lib/python3.14/site-packages/jsonpickle/unpickler.py", "source_location": "L676"}, {"id": "unpickler_unpickler_restore_state", "label": "._restore_state()", "file_type": "code", "source_file": "graphify-env/lib/python3.14/site-packages/jsonpickle/unpickler.py", "source_location": "L751"}, {"id": "unpickler_unpickler_restore_object_instance_variables", "label": "._restore_object_instance_variables()", "file_type": "code", "source_file": "graphify-env/lib/python3.14/site-packages/jsonpickle/unpickler.py", "source_location": "L784"}, {"id": "unpickler_unpickler_restore_object_instance", "label": "._restore_object_instance()", "file_type": "code", "source_file": "graphify-env/lib/python3.14/site-packages/jsonpickle/unpickler.py", "source_location": "L801"}, {"id": "unpickler_unpickler_restore_object", "label": "._restore_object()", "file_type": "code", "source_file": "graphify-env/lib/python3.14/site-packages/jsonpickle/unpickler.py", "source_location": "L860"}, {"id": "unpickler_unpickler_restore_function", "label": "._restore_function()", "file_type": "code", "source_file": "graphify-env/lib/python3.14/site-packages/jsonpickle/unpickler.py", "source_location": "L878"}, {"id": "unpickler_unpickler_restore_set", "label": "._restore_set()", "file_type": "code", "source_file": "graphify-env/lib/python3.14/site-packages/jsonpickle/unpickler.py", "source_location": "L881"}, {"id": "unpickler_unpickler_restore_dict", "label": "._restore_dict()", "file_type": "code", "source_file": "graphify-env/lib/python3.14/site-packages/jsonpickle/unpickler.py", "source_location": "L887"}, {"id": "unpickler_unpickler_restore_tuple", "label": "._restore_tuple()", "file_type": "code", "source_file": "graphify-env/lib/python3.14/site-packages/jsonpickle/unpickler.py", "source_location": "L937"}, {"id": "unpickler_unpickler_restore_tags", "label": "._restore_tags()", "file_type": "code", "source_file": "graphify-env/lib/python3.14/site-packages/jsonpickle/unpickler.py", "source_location": "L943"}, {"id": "unpickler_rationale_27", "label": "Convert a JSON string into a Python object.      :param backend: If set to an in", "file_type": "rationale", "source_file": "graphify-env/lib/python3.14/site-packages/jsonpickle/unpickler.py", "source_location": "L27"}, {"id": "unpickler_rationale_107", "label": "Workaround unreliable hasattr() availability on sqlalchemy objects", "file_type": "rationale", "source_file": "graphify-env/lib/python3.14/site-packages/jsonpickle/unpickler.py", "source_location": "L107"}, {"id": "unpickler_rationale_116", "label": "Has this key a special object that has been encoded to JSON?", "file_type": "rationale", "source_file": "graphify-env/lib/python3.14/site-packages/jsonpickle/unpickler.py", "source_location": "L116"}, {"id": "unpickler_rationale_121", "label": "Proxies are dummy objects that are later replaced by real instances      The `re", "file_type": "rationale", "source_file": "graphify-env/lib/python3.14/site-packages/jsonpickle/unpickler.py", "source_location": "L121"}, {"id": "unpickler_rationale_172", "label": "Use setattr to update a proxy entry", "file_type": "rationale", "source_file": "graphify-env/lib/python3.14/site-packages/jsonpickle/unpickler.py", "source_location": "L172"}, {"id": "unpickler_rationale_177", "label": "Use obj[key] assignments to update a proxy entry", "file_type": "rationale", "source_file": "graphify-env/lib/python3.14/site-packages/jsonpickle/unpickler.py", "source_location": "L177"}, {"id": "unpickler_rationale_182", "label": "Loads the module and returns the class.      >>> cls = loadclass('datetime.datet", "file_type": "rationale", "source_file": "graphify-env/lib/python3.14/site-packages/jsonpickle/unpickler.py", "source_location": "L182"}, {"id": "unpickler_rationale_226", "label": "Helper class that tests to see if the obj is a dictionary     and contains a par", "file_type": "rationale", "source_file": "graphify-env/lib/python3.14/site-packages/jsonpickle/unpickler.py", "source_location": "L226"}, {"id": "unpickler_rationale_243", "label": "Return arguments suitable for __new__()", "file_type": "rationale", "source_file": "graphify-env/lib/python3.14/site-packages/jsonpickle/unpickler.py", "source_location": "L243"}, {"id": "unpickler_rationale_269", "label": "A trivial class that can be instantiated with no args", "file_type": "rationale", "source_file": "graphify-env/lib/python3.14/site-packages/jsonpickle/unpickler.py", "source_location": "L269"}, {"id": "unpickler_rationale_275", "label": "Implement the mandated strategy for dealing with classic classes     which canno", "file_type": "rationale", "source_file": "graphify-env/lib/python3.14/site-packages/jsonpickle/unpickler.py", "source_location": "L275"}, {"id": "unpickler_rationale_286", "label": "Returns an instance of the object from the object's repr() string.     It involv", "file_type": "rationale", "source_file": "graphify-env/lib/python3.14/site-packages/jsonpickle/unpickler.py", "source_location": "L286"}, {"id": "unpickler_rationale_308", "label": "Returns a reference to a module.      >>> fn = _loadmodule('datetime/datetime.da", "file_type": "rationale", "source_file": "graphify-env/lib/python3.14/site-packages/jsonpickle/unpickler.py", "source_location": "L308"}, {"id": "unpickler_rationale_333", "label": "Helper class that tests to see if the obj is a dictionary     and contains a par", "file_type": "rationale", "source_file": "graphify-env/lib/python3.14/site-packages/jsonpickle/unpickler.py", "source_location": "L333"}, {"id": "unpickler_rationale_350", "label": "A function that returns its input as-is", "file_type": "rationale", "source_file": "graphify-env/lib/python3.14/site-packages/jsonpickle/unpickler.py", "source_location": "L350"}, {"id": "unpickler_rationale_374", "label": "Resets the object's internal state.", "file_type": "rationale", "source_file": "graphify-env/lib/python3.14/site-packages/jsonpickle/unpickler.py", "source_location": "L374"}, {"id": "unpickler_rationale_390", "label": "Replace proxies with their corresponding instances", "file_type": "rationale", "source_file": "graphify-env/lib/python3.14/site-packages/jsonpickle/unpickler.py", "source_location": "L390"}, {"id": "unpickler_rationale_405", "label": "Restores a flattened object to its original python state.          Simply return", "file_type": "rationale", "source_file": "graphify-env/lib/python3.14/site-packages/jsonpickle/unpickler.py", "source_location": "L405"}, {"id": "unpickler_rationale_426", "label": "Register one or more classes          :param classes: sequence of classes or a s", "file_type": "rationale", "source_file": "graphify-env/lib/python3.14/site-packages/jsonpickle/unpickler.py", "source_location": "L426"}, {"id": "unpickler_rationale_458", "label": "Calculates the name of the current location in the JSON stack.          This is", "file_type": "rationale", "source_file": "graphify-env/lib/python3.14/site-packages/jsonpickle/unpickler.py", "source_location": "L458"}, {"id": "unpickler_rationale_525", "label": "Supports restoring with all elements of __reduce__ as per pep 307.         Assum", "file_type": "rationale", "source_file": "graphify-env/lib/python3.14/site-packages/jsonpickle/unpickler.py", "source_location": "L525"}, {"id": "unpickler_rationale_647", "label": "Restore a possibly pickled key", "file_type": "rationale", "source_file": "graphify-env/lib/python3.14/site-packages/jsonpickle/unpickler.py", "source_location": "L647"}, {"id": "unpickler_rationale_659", "label": "Return a callable that restores keys          This function is responsible for r", "file_type": "rationale", "source_file": "graphify-env/lib/python3.14/site-packages/jsonpickle/unpickler.py", "source_location": "L659"}, {"id": "unpickler_rationale_944", "label": "Return the restoration function for the specified object", "file_type": "rationale", "source_file": "graphify-env/lib/python3.14/site-packages/jsonpickle/unpickler.py", "source_location": "L944"}], "edges": [{"source": "unpickler", "target": "dataclasses", "relation": "imports", "confidence": "EXTRACTED", "source_file": "graphify-env/lib/python3.14/site-packages/jsonpickle/unpickler.py", "source_location": "L7", "weight": 1.0}, {"source": "unpickler", "target": "sys", "relation": "imports", "confidence": "EXTRACTED", "source_file": "graphify-env/lib/python3.14/site-packages/jsonpickle/unpickler.py", "source_location": "L8", "weight": 1.0}, {"source": "unpickler", "target": "warnings", "relation": "imports", "confidence": "EXTRACTED", "source_file": "graphify-env/lib/python3.14/site-packages/jsonpickle/unpickler.py", "source_location": "L9", "weight": 1.0}, {"source": "unpickler", "target": "", "relation": "imports_from", "confidence": "EXTRACTED", "source_file": "graphify-env/lib/python3.14/site-packages/jsonpickle/unpickler.py", "source_location": "L11", "weight": 1.0}, {"source": "unpickler", "target": "backend", "relation": "imports_from", "confidence": "EXTRACTED", "source_file": "graphify-env/lib/python3.14/site-packages/jsonpickle/unpickler.py", "source_location": "L12", "weight": 1.0}, {"source": "unpickler", "target": "unpickler_decode", "relation": "contains", "confidence": "EXTRACTED", "source_file": "graphify-env/lib/python3.14/site-packages/jsonpickle/unpickler.py", "source_location": "L15", "weight": 1.0}, {"source": "unpickler", "target": "unpickler_safe_hasattr", "relation": "contains", "confidence": "EXTRACTED", "source_file": "graphify-env/lib/python3.14/site-packages/jsonpickle/unpickler.py", "source_location": "L106", "weight": 1.0}, {"source": "unpickler", "target": "unpickler_is_json_key", "relation": "contains", "confidence": "EXTRACTED", "source_file": "graphify-env/lib/python3.14/site-packages/jsonpickle/unpickler.py", "source_location": "L115", "weight": 1.0}, {"source": "unpickler", "target": "unpickler_proxy", "relation": "contains", "confidence": "EXTRACTED", "source_file": "graphify-env/lib/python3.14/site-packages/jsonpickle/unpickler.py", "source_location": "L120", "weight": 1.0}, {"source": "unpickler_proxy", "target": "unpickler_proxy_init", "relation": "method", "confidence": "EXTRACTED", "source_file": "graphify-env/lib/python3.14/site-packages/jsonpickle/unpickler.py", "source_location": "L149", "weight": 1.0}, {"source": "unpickler_proxy", "target": "unpickler_proxy_get", "relation": "method", "confidence": "EXTRACTED", "source_file": "graphify-env/lib/python3.14/site-packages/jsonpickle/unpickler.py", "source_location": "L152", "weight": 1.0}, {"source": "unpickler_proxy", "target": "unpickler_proxy_reset", "relation": "method", "confidence": "EXTRACTED", "source_file": "graphify-env/lib/python3.14/site-packages/jsonpickle/unpickler.py", "source_location": "L155", "weight": 1.0}, {"source": "unpickler", "target": "unpickler_idproxy", "relation": "contains", "confidence": "EXTRACTED", "source_file": "graphify-env/lib/python3.14/site-packages/jsonpickle/unpickler.py", "source_location": "L159", "weight": 1.0}, {"source": "unpickler_idproxy", "target": "unpickler_proxy", "relation": "inherits", "confidence": "EXTRACTED", "source_file": "graphify-env/lib/python3.14/site-packages/jsonpickle/unpickler.py", "source_location": "L159", "weight": 1.0}, {"source": "unpickler_idproxy", "target": "unpickler_idproxy_init", "relation": "method", "confidence": "EXTRACTED", "source_file": "graphify-env/lib/python3.14/site-packages/jsonpickle/unpickler.py", "source_location": "L160", "weight": 1.0}, {"source": "unpickler_idproxy", "target": "unpickler_idproxy_get", "relation": "method", "confidence": "EXTRACTED", "source_file": "graphify-env/lib/python3.14/site-packages/jsonpickle/unpickler.py", "source_location": "L164", "weight": 1.0}, {"source": "unpickler", "target": "unpickler_obj_setattr", "relation": "contains", "confidence": "EXTRACTED", "source_file": "graphify-env/lib/python3.14/site-packages/jsonpickle/unpickler.py", "source_location": "L171", "weight": 1.0}, {"source": "unpickler", "target": "unpickler_obj_setvalue", "relation": "contains", "confidence": "EXTRACTED", "source_file": "graphify-env/lib/python3.14/site-packages/jsonpickle/unpickler.py", "source_location": "L176", "weight": 1.0}, {"source": "unpickler", "target": "unpickler_loadclass", "relation": "contains", "confidence": "EXTRACTED", "source_file": "graphify-env/lib/python3.14/site-packages/jsonpickle/unpickler.py", "source_location": "L181", "weight": 1.0}, {"source": "unpickler", "target": "unpickler_has_tag", "relation": "contains", "confidence": "EXTRACTED", "source_file": "graphify-env/lib/python3.14/site-packages/jsonpickle/unpickler.py", "source_location": "L225", "weight": 1.0}, {"source": "unpickler", "target": "unpickler_getargs", "relation": "contains", "confidence": "EXTRACTED", "source_file": "graphify-env/lib/python3.14/site-packages/jsonpickle/unpickler.py", "source_location": "L242", "weight": 1.0}, {"source": "unpickler", "target": "unpickler_trivialclassic", "relation": "contains", "confidence": "EXTRACTED", "source_file": "graphify-env/lib/python3.14/site-packages/jsonpickle/unpickler.py", "source_location": "L268", "weight": 1.0}, {"source": "unpickler", "target": "unpickler_make_blank_classic", "relation": "contains", "confidence": "EXTRACTED", "source_file": "graphify-env/lib/python3.14/site-packages/jsonpickle/unpickler.py", "source_location": "L274", "weight": 1.0}, {"source": "unpickler", "target": "unpickler_loadrepr", "relation": "contains", "confidence": "EXTRACTED", "source_file": "graphify-env/lib/python3.14/site-packages/jsonpickle/unpickler.py", "source_location": "L285", "weight": 1.0}, {"source": "unpickler", "target": "unpickler_loadmodule", "relation": "contains", "confidence": "EXTRACTED", "source_file": "graphify-env/lib/python3.14/site-packages/jsonpickle/unpickler.py", "source_location": "L307", "weight": 1.0}, {"source": "unpickler", "target": "unpickler_has_tag_dict", "relation": "contains", "confidence": "EXTRACTED", "source_file": "graphify-env/lib/python3.14/site-packages/jsonpickle/unpickler.py", "source_location": "L332", "weight": 1.0}, {"source": "unpickler", "target": "unpickler_passthrough", "relation": "contains", "confidence": "EXTRACTED", "source_file": "graphify-env/lib/python3.14/site-packages/jsonpickle/unpickler.py", "source_location": "L349", "weight": 1.0}, {"source": "unpickler", "target": "unpickler_unpickler", "relation": "contains", "confidence": "EXTRACTED", "source_file": "graphify-env/lib/python3.14/site-packages/jsonpickle/unpickler.py", "source_location": "L354", "weight": 1.0}, {"source": "unpickler_unpickler", "target": "unpickler_unpickler_init", "relation": "method", "confidence": "EXTRACTED", "source_file": "graphify-env/lib/python3.14/site-packages/jsonpickle/unpickler.py", "source_location": "L355", "weight": 1.0}, {"source": "unpickler_unpickler", "target": "unpickler_unpickler_reset", "relation": "method", "confidence": "EXTRACTED", "source_file": "graphify-env/lib/python3.14/site-packages/jsonpickle/unpickler.py", "source_location": "L373", "weight": 1.0}, {"source": "unpickler_unpickler", "target": "unpickler_unpickler_swap_proxies", "relation": "method", "confidence": "EXTRACTED", "source_file": "graphify-env/lib/python3.14/site-packages/jsonpickle/unpickler.py", "source_location": "L389", "weight": 1.0}, {"source": "unpickler_unpickler", "target": "unpickler_unpickler_restore", "relation": "method", "confidence": "EXTRACTED", "source_file": "graphify-env/lib/python3.14/site-packages/jsonpickle/unpickler.py", "source_location": "L395", "weight": 1.0}, {"source": "unpickler_unpickler", "target": "unpickler_unpickler_restore", "relation": "method", "confidence": "EXTRACTED", "source_file": "graphify-env/lib/python3.14/site-packages/jsonpickle/unpickler.py", "source_location": "L404", "weight": 1.0}, {"source": "unpickler_unpickler", "target": "unpickler_unpickler_register_classes", "relation": "method", "confidence": "EXTRACTED", "source_file": "graphify-env/lib/python3.14/site-packages/jsonpickle/unpickler.py", "source_location": "L425", "weight": 1.0}, {"source": "unpickler_unpickler", "target": "unpickler_unpickler_restore_base64", "relation": "method", "confidence": "EXTRACTED", "source_file": "graphify-env/lib/python3.14/site-packages/jsonpickle/unpickler.py", "source_location": "L445", "weight": 1.0}, {"source": "unpickler_unpickler", "target": "unpickler_unpickler_restore_base85", "relation": "method", "confidence": "EXTRACTED", "source_file": "graphify-env/lib/python3.14/site-packages/jsonpickle/unpickler.py", "source_location": "L451", "weight": 1.0}, {"source": "unpickler_unpickler", "target": "unpickler_unpickler_refname", "relation": "method", "confidence": "EXTRACTED", "source_file": "graphify-env/lib/python3.14/site-packages/jsonpickle/unpickler.py", "source_location": "L457", "weight": 1.0}, {"source": "unpickler_unpickler", "target": "unpickler_unpickler_mkref", "relation": "method", "confidence": "EXTRACTED", "source_file": "graphify-env/lib/python3.14/site-packages/jsonpickle/unpickler.py", "source_location": "L481", "weight": 1.0}, {"source": "unpickler_unpickler", "target": "unpickler_unpickler_restore_list", "relation": "method", "confidence": "EXTRACTED", "source_file": "graphify-env/lib/python3.14/site-packages/jsonpickle/unpickler.py", "source_location": "L493", "weight": 1.0}, {"source": "unpickler_unpickler", "target": "unpickler_unpickler_restore_iterator", "relation": "method", "confidence": "EXTRACTED", "source_file": "graphify-env/lib/python3.14/site-packages/jsonpickle/unpickler.py", "source_location": "L507", "weight": 1.0}, {"source": "unpickler_unpickler", "target": "unpickler_unpickler_swapref", "relation": "method", "confidence": "EXTRACTED", "source_file": "graphify-env/lib/python3.14/site-packages/jsonpickle/unpickler.py", "source_location": "L513", "weight": 1.0}, {"source": "unpickler_unpickler", "target": "unpickler_unpickler_restore_reduce", "relation": "method", "confidence": "EXTRACTED", "source_file": "graphify-env/lib/python3.14/site-packages/jsonpickle/unpickler.py", "source_location": "L524", "weight": 1.0}, {"source": "unpickler_unpickler", "target": "unpickler_unpickler_restore_id", "relation": "method", "confidence": "EXTRACTED", "source_file": "graphify-env/lib/python3.14/site-packages/jsonpickle/unpickler.py", "source_location": "L598", "weight": 1.0}, {"source": "unpickler_unpickler", "target": "unpickler_unpickler_restore_type", "relation": "method", "confidence": "EXTRACTED", "source_file": "graphify-env/lib/python3.14/site-packages/jsonpickle/unpickler.py", "source_location": "L607", "weight": 1.0}, {"source": "unpickler_unpickler", "target": "unpickler_unpickler_restore_module", "relation": "method", "confidence": "EXTRACTED", "source_file": "graphify-env/lib/python3.14/site-packages/jsonpickle/unpickler.py", "source_location": "L613", "weight": 1.0}, {"source": "unpickler_unpickler", "target": "unpickler_unpickler_restore_repr_safe", "relation": "method", "confidence": "EXTRACTED", "source_file": "graphify-env/lib/python3.14/site-packages/jsonpickle/unpickler.py", "source_location": "L617", "weight": 1.0}, {"source": "unpickler_unpickler", "target": "unpickler_unpickler_restore_repr", "relation": "method", "confidence": "EXTRACTED", "source_file": "graphify-env/lib/python3.14/site-packages/jsonpickle/unpickler.py", "source_location": "L621", "weight": 1.0}, {"source": "unpickler_unpickler", "target": "unpickler_unpickler_loadfactory", "relation": "method", "confidence": "EXTRACTED", "source_file": "graphify-env/lib/python3.14/site-packages/jsonpickle/unpickler.py", "source_location": "L625", "weight": 1.0}, {"source": "unpickler_unpickler", "target": "unpickler_unpickler_process_missing", "relation": "method", "confidence": "EXTRACTED", "source_file": "graphify-env/lib/python3.14/site-packages/jsonpickle/unpickler.py", "source_location": "L633", "weight": 1.0}, {"source": "unpickler_unpickler", "target": "unpickler_unpickler_restore_pickled_key", "relation": "method", "confidence": "EXTRACTED", "source_file": "graphify-env/lib/python3.14/site-packages/jsonpickle/unpickler.py", "source_location": "L646", "weight": 1.0}, {"source": "unpickler_unpickler", "target": "unpickler_unpickler_restore_key_fn", "relation": "method", "confidence": "EXTRACTED", "source_file": "graphify-env/lib/python3.14/site-packages/jsonpickle/unpickler.py", "source_location": "L658", "weight": 1.0}, {"source": "unpickler_unpickler", "target": "unpickler_unpickler_restore_from_dict", "relation": "method", "confidence": "EXTRACTED", "source_file": "graphify-env/lib/python3.14/site-packages/jsonpickle/unpickler.py", "source_location": "L676", "weight": 1.0}, {"source": "unpickler_unpickler", "target": "unpickler_unpickler_restore_state", "relation": "method", "confidence": "EXTRACTED", "source_file": "graphify-env/lib/python3.14/site-packages/jsonpickle/unpickler.py", "source_location": "L751", "weight": 1.0}, {"source": "unpickler_unpickler", "target": "unpickler_unpickler_restore_object_instance_variables", "relation": "method", "confidence": "EXTRACTED", "source_file": "graphify-env/lib/python3.14/site-packages/jsonpickle/unpickler.py", "source_location": "L784", "weight": 1.0}, {"source": "unpickler_unpickler", "target": "unpickler_unpickler_restore_object_instance", "relation": "method", "confidence": "EXTRACTED", "source_file": "graphify-env/lib/python3.14/site-packages/jsonpickle/unpickler.py", "source_location": "L801", "weight": 1.0}, {"source": "unpickler_unpickler", "target": "unpickler_unpickler_restore_object", "relation": "method", "confidence": "EXTRACTED", "source_file": "graphify-env/lib/python3.14/site-packages/jsonpickle/unpickler.py", "source_location": "L860", "weight": 1.0}, {"source": "unpickler_unpickler", "target": "unpickler_unpickler_restore_function", "relation": "method", "confidence": "EXTRACTED", "source_file": "graphify-env/lib/python3.14/site-packages/jsonpickle/unpickler.py", "source_location": "L878", "weight": 1.0}, {"source": "unpickler_unpickler", "target": "unpickler_unpickler_restore_set", "relation": "method", "confidence": "EXTRACTED", "source_file": "graphify-env/lib/python3.14/site-packages/jsonpickle/unpickler.py", "source_location": "L881", "weight": 1.0}, {"source": "unpickler_unpickler", "target": "unpickler_unpickler_restore_dict", "relation": "method", "confidence": "EXTRACTED", "source_file": "graphify-env/lib/python3.14/site-packages/jsonpickle/unpickler.py", "source_location": "L887", "weight": 1.0}, {"source": "unpickler_unpickler", "target": "unpickler_unpickler_restore_tuple", "relation": "method", "confidence": "EXTRACTED", "source_file": "graphify-env/lib/python3.14/site-packages/jsonpickle/unpickler.py", "source_location": "L937", "weight": 1.0}, {"source": "unpickler_unpickler", "target": "unpickler_unpickler_restore_tags", "relation": "method", "confidence": "EXTRACTED", "source_file": "graphify-env/lib/python3.14/site-packages/jsonpickle/unpickler.py", "source_location": "L943", "weight": 1.0}, {"source": "unpickler_decode", "target": "unpickler_unpickler", "relation": "calls", "confidence": "INFERRED", "source_file": "graphify-env/lib/python3.14/site-packages/jsonpickle/unpickler.py", "source_location": "L94", "weight": 0.8}, {"source": "unpickler_obj_setattr", "target": "unpickler_idproxy_get", "relation": "calls", "confidence": "INFERRED", "source_file": "graphify-env/lib/python3.14/site-packages/jsonpickle/unpickler.py", "source_location": "L173", "weight": 0.8}, {"source": "unpickler_obj_setvalue", "target": "unpickler_idproxy_get", "relation": "calls", "confidence": "INFERRED", "source_file": "graphify-env/lib/python3.14/site-packages/jsonpickle/unpickler.py", "source_location": "L178", "weight": 0.8}, {"source": "unpickler_getargs", "target": "unpickler_has_tag", "relation": "calls", "confidence": "INFERRED", "source_file": "graphify-env/lib/python3.14/site-packages/jsonpickle/unpickler.py", "source_location": "L245", "weight": 0.8}, {"source": "unpickler_getargs", "target": "unpickler_loadclass", "relation": "calls", "confidence": "INFERRED", "source_file": "graphify-env/lib/python3.14/site-packages/jsonpickle/unpickler.py", "source_location": "L259", "weight": 0.8}, {"source": "unpickler_make_blank_classic", "target": "unpickler_trivialclassic", "relation": "calls", "confidence": "INFERRED", "source_file": "graphify-env/lib/python3.14/site-packages/jsonpickle/unpickler.py", "source_location": "L280", "weight": 0.8}, {"source": "unpickler_unpickler_init", "target": "unpickler_unpickler_reset", "relation": "calls", "confidence": "INFERRED", "source_file": "graphify-env/lib/python3.14/site-packages/jsonpickle/unpickler.py", "source_location": "L371", "weight": 0.8}, {"source": "unpickler_unpickler_restore", "target": "unpickler_unpickler_restore_tags", "relation": "calls", "confidence": "INFERRED", "source_file": "graphify-env/lib/python3.14/site-packages/jsonpickle/unpickler.py", "source_location": "L401", "weight": 0.8}, {"source": "unpickler_unpickler_restore", "target": "unpickler_unpickler_reset", "relation": "calls", "confidence": "INFERRED", "source_file": "graphify-env/lib/python3.14/site-packages/jsonpickle/unpickler.py", "source_location": "L417", "weight": 0.8}, {"source": "unpickler_unpickler_restore", "target": "unpickler_unpickler_register_classes", "relation": "calls", "confidence": "INFERRED", "source_file": "graphify-env/lib/python3.14/site-packages/jsonpickle/unpickler.py", "source_location": "L419", "weight": 0.8}, {"source": "unpickler_unpickler_restore", "target": "unpickler_unpickler_swap_proxies", "relation": "calls", "confidence": "INFERRED", "source_file": "graphify-env/lib/python3.14/site-packages/jsonpickle/unpickler.py", "source_location": "L422", "weight": 0.8}, {"source": "unpickler_unpickler_mkref", "target": "unpickler_unpickler_refname", "relation": "calls", "confidence": "INFERRED", "source_file": "graphify-env/lib/python3.14/site-packages/jsonpickle/unpickler.py", "source_location": "L490", "weight": 0.8}, {"source": "unpickler_unpickler_restore_list", "target": "unpickler_unpickler_mkref", "relation": "calls", "confidence": "INFERRED", "source_file": "graphify-env/lib/python3.14/site-packages/jsonpickle/unpickler.py", "source_location": "L495", "weight": 0.8}, {"source": "unpickler_unpickler_restore_list", "target": "unpickler_unpickler_restore", "relation": "calls", "confidence": "INFERRED", "source_file": "graphify-env/lib/python3.14/site-packages/jsonpickle/unpickler.py", "source_location": "L496", "weight": 0.8}, {"source": "unpickler_unpickler_restore_iterator", "target": "unpickler_unpickler_restore_list", "relation": "calls", "confidence": "INFERRED", "source_file": "graphify-env/lib/python3.14/site-packages/jsonpickle/unpickler.py", "source_location": "L509", "weight": 0.8}, {"source": "unpickler_unpickler_swapref", "target": "unpickler_unpickler_refname", "relation": "calls", "confidence": "INFERRED", "source_file": "graphify-env/lib/python3.14/site-packages/jsonpickle/unpickler.py", "source_location": "L522", "weight": 0.8}, {"source": "unpickler_unpickler_restore_reduce", "target": "unpickler_proxy", "relation": "calls", "confidence": "INFERRED", "source_file": "graphify-env/lib/python3.14/site-packages/jsonpickle/unpickler.py", "source_location": "L530", "weight": 0.8}, {"source": "unpickler_unpickler_restore_reduce", "target": "unpickler_unpickler_mkref", "relation": "calls", "confidence": "INFERRED", "source_file": "graphify-env/lib/python3.14/site-packages/jsonpickle/unpickler.py", "source_location": "L531", "weight": 0.8}, {"source": "unpickler_unpickler_restore_reduce", "target": "unpickler_unpickler_reset", "relation": "calls", "confidence": "INFERRED", "source_file": "graphify-env/lib/python3.14/site-packages/jsonpickle/unpickler.py", "source_location": "L536", "weight": 0.8}, {"source": "unpickler_unpickler_restore_reduce", "target": "unpickler_unpickler_swapref", "relation": "calls", "confidence": "INFERRED", "source_file": "graphify-env/lib/python3.14/site-packages/jsonpickle/unpickler.py", "source_location": "L537", "weight": 0.8}, {"source": "unpickler_unpickler_restore_reduce", "target": "unpickler_unpickler_restore", "relation": "calls", "confidence": "INFERRED", "source_file": "graphify-env/lib/python3.14/site-packages/jsonpickle/unpickler.py", "source_location": "L547", "weight": 0.8}, {"source": "unpickler_unpickler_restore_id", "target": "unpickler_idproxy", "relation": "calls", "confidence": "INFERRED", "source_file": "graphify-env/lib/python3.14/site-packages/jsonpickle/unpickler.py", "source_location": "L603", "weight": 0.8}, {"source": "unpickler_unpickler_restore_type", "target": "unpickler_loadclass", "relation": "calls", "confidence": "INFERRED", "source_file": "graphify-env/lib/python3.14/site-packages/jsonpickle/unpickler.py", "source_location": "L608", "weight": 0.8}, {"source": "unpickler_unpickler_restore_module", "target": "unpickler_loadmodule", "relation": "calls", "confidence": "INFERRED", "source_file": "graphify-env/lib/python3.14/site-packages/jsonpickle/unpickler.py", "source_location": "L614", "weight": 0.8}, {"source": "unpickler_unpickler_restore_module", "target": "unpickler_unpickler_mkref", "relation": "calls", "confidence": "INFERRED", "source_file": "graphify-env/lib/python3.14/site-packages/jsonpickle/unpickler.py", "source_location": "L615", "weight": 0.8}, {"source": "unpickler_unpickler_restore_repr_safe", "target": "unpickler_loadmodule", "relation": "calls", "confidence": "INFERRED", "source_file": "graphify-env/lib/python3.14/site-packages/jsonpickle/unpickler.py", "source_location": "L618", "weight": 0.8}, {"source": "unpickler_unpickler_restore_repr_safe", "target": "unpickler_unpickler_mkref", "relation": "calls", "confidence": "INFERRED", "source_file": "graphify-env/lib/python3.14/site-packages/jsonpickle/unpickler.py", "source_location": "L619", "weight": 0.8}, {"source": "unpickler_unpickler_restore_repr", "target": "unpickler_loadrepr", "relation": "calls", "confidence": "INFERRED", "source_file": "graphify-env/lib/python3.14/site-packages/jsonpickle/unpickler.py", "source_location": "L622", "weight": 0.8}, {"source": "unpickler_unpickler_restore_repr", "target": "unpickler_unpickler_mkref", "relation": "calls", "confidence": "INFERRED", "source_file": "graphify-env/lib/python3.14/site-packages/jsonpickle/unpickler.py", "source_location": "L623", "weight": 0.8}, {"source": "unpickler_unpickler_loadfactory", "target": "unpickler_unpickler_restore", "relation": "calls", "confidence": "INFERRED", "source_file": "graphify-env/lib/python3.14/site-packages/jsonpickle/unpickler.py", "source_location": "L631", "weight": 0.8}, {"source": "unpickler_unpickler_restore_pickled_key", "target": "unpickler_is_json_key", "relation": "calls", "confidence": "INFERRED", "source_file": "graphify-env/lib/python3.14/site-packages/jsonpickle/unpickler.py", "source_location": "L648", "weight": 0.8}, {"source": "unpickler_unpickler_restore_pickled_key", "target": "unpickler_decode", "relation": "calls", "confidence": "INFERRED", "source_file": "graphify-env/lib/python3.14/site-packages/jsonpickle/unpickler.py", "source_location": "L649", "weight": 0.8}, {"source": "unpickler_unpickler_restore_from_dict", "target": "unpickler_unpickler_restore_key_fn", "relation": "calls", "confidence": "INFERRED", "source_file": "graphify-env/lib/python3.14/site-packages/jsonpickle/unpickler.py", "source_location": "L679", "weight": 0.8}, {"source": "unpickler_unpickler_restore_from_dict", "target": "unpickler_unpickler_restore", "relation": "calls", "confidence": "INFERRED", "source_file": "graphify-env/lib/python3.14/site-packages/jsonpickle/unpickler.py", "source_location": "L695", "weight": 0.8}, {"source": "unpickler_unpickler_restore_state", "target": "unpickler_unpickler_restore", "relation": "calls", "confidence": "INFERRED", "source_file": "graphify-env/lib/python3.14/site-packages/jsonpickle/unpickler.py", "source_location": "L752", "weight": 0.8}, {"source": "unpickler_unpickler_restore_state", "target": "unpickler_unpickler_restore_from_dict", "relation": "calls", "confidence": "INFERRED", "source_file": "graphify-env/lib/python3.14/site-packages/jsonpickle/unpickler.py", "source_location": "L763", "weight": 0.8}, {"source": "unpickler_unpickler_restore_object_instance_variables", "target": "unpickler_unpickler_restore_from_dict", "relation": "calls", "confidence": "INFERRED", "source_file": "graphify-env/lib/python3.14/site-packages/jsonpickle/unpickler.py", "source_location": "L785", "weight": 0.8}, {"source": "unpickler_unpickler_restore_object_instance_variables", "target": "unpickler_has_tag", "relation": "calls", "confidence": "INFERRED", "source_file": "graphify-env/lib/python3.14/site-packages/jsonpickle/unpickler.py", "source_location": "L788", "weight": 0.8}, {"source": "unpickler_unpickler_restore_object_instance_variables", "target": "unpickler_unpickler_restore", "relation": "calls", "confidence": "INFERRED", "source_file": "graphify-env/lib/python3.14/site-packages/jsonpickle/unpickler.py", "source_location": "L791", "weight": 0.8}, {"source": "unpickler_unpickler_restore_object_instance_variables", "target": "unpickler_unpickler_restore_state", "relation": "calls", "confidence": "INFERRED", "source_file": "graphify-env/lib/python3.14/site-packages/jsonpickle/unpickler.py", "source_location": "L797", "weight": 0.8}, {"source": "unpickler_unpickler_restore_object_instance", "target": "unpickler_proxy", "relation": "calls", "confidence": "INFERRED", "source_file": "graphify-env/lib/python3.14/site-packages/jsonpickle/unpickler.py", "source_location": "L804", "weight": 0.8}, {"source": "unpickler_unpickler_restore_object_instance", "target": "unpickler_unpickler_mkref", "relation": "calls", "confidence": "INFERRED", "source_file": "graphify-env/lib/python3.14/site-packages/jsonpickle/unpickler.py", "source_location": "L805", "weight": 0.8}, {"source": "unpickler_unpickler_restore_object_instance", "target": "unpickler_unpickler_loadfactory", "relation": "calls", "confidence": "INFERRED", "source_file": "graphify-env/lib/python3.14/site-packages/jsonpickle/unpickler.py", "source_location": "L809", "weight": 0.8}, {"source": "unpickler_unpickler_restore_object_instance", "target": "unpickler_has_tag", "relation": "calls", "confidence": "INFERRED", "source_file": "graphify-env/lib/python3.14/site-packages/jsonpickle/unpickler.py", "source_location": "L811", "weight": 0.8}, {"source": "unpickler_unpickler_restore_object_instance", "target": "unpickler_getargs", "relation": "calls", "confidence": "INFERRED", "source_file": "graphify-env/lib/python3.14/site-packages/jsonpickle/unpickler.py", "source_location": "L814", "weight": 0.8}, {"source": "unpickler_unpickler_restore_object_instance", "target": "unpickler_unpickler_restore", "relation": "calls", "confidence": "INFERRED", "source_file": "graphify-env/lib/python3.14/site-packages/jsonpickle/unpickler.py", "source_location": "L817", "weight": 0.8}, {"source": "unpickler_unpickler_restore_object_instance", "target": "unpickler_make_blank_classic", "relation": "calls", "confidence": "INFERRED", "source_file": "graphify-env/lib/python3.14/site-packages/jsonpickle/unpickler.py", "source_location": "L840", "weight": 0.8}, {"source": "unpickler_unpickler_restore_object_instance", "target": "unpickler_unpickler_process_missing", "relation": "calls", "confidence": "INFERRED", "source_file": "graphify-env/lib/python3.14/site-packages/jsonpickle/unpickler.py", "source_location": "L842", "weight": 0.8}, {"source": "unpickler_unpickler_restore_object_instance", "target": "unpickler_unpickler_reset", "relation": "calls", "confidence": "INFERRED", "source_file": "graphify-env/lib/python3.14/site-packages/jsonpickle/unpickler.py", "source_location": "L845", "weight": 0.8}, {"source": "unpickler_unpickler_restore_object_instance", "target": "unpickler_unpickler_swapref", "relation": "calls", "confidence": "INFERRED", "source_file": "graphify-env/lib/python3.14/site-packages/jsonpickle/unpickler.py", "source_location": "L846", "weight": 0.8}, {"source": "unpickler_unpickler_restore_object_instance", "target": "unpickler_unpickler_restore_object_instance_variables", "relation": "calls", "confidence": "INFERRED", "source_file": "graphify-env/lib/python3.14/site-packages/jsonpickle/unpickler.py", "source_location": "L851", "weight": 0.8}, {"source": "unpickler_unpickler_restore_object_instance", "target": "unpickler_safe_hasattr", "relation": "calls", "confidence": "INFERRED", "source_file": "graphify-env/lib/python3.14/site-packages/jsonpickle/unpickler.py", "source_location": "L853", "weight": 0.8}, {"source": "unpickler_unpickler_restore_object_instance", "target": "unpickler_idproxy_get", "relation": "calls", "confidence": "INFERRED", "source_file": "graphify-env/lib/python3.14/site-packages/jsonpickle/unpickler.py", "source_location": "L856", "weight": 0.8}, {"source": "unpickler_unpickler_restore_object", "target": "unpickler_loadclass", "relation": "calls", "confidence": "INFERRED", "source_file": "graphify-env/lib/python3.14/site-packages/jsonpickle/unpickler.py", "source_location": "L862", "weight": 0.8}, {"source": "unpickler_unpickler_restore_object", "target": "unpickler_idproxy_get", "relation": "calls", "confidence": "INFERRED", "source_file": "graphify-env/lib/python3.14/site-packages/jsonpickle/unpickler.py", "source_location": "L863", "weight": 0.8}, {"source": "unpickler_unpickler_restore_object", "target": "unpickler_proxy", "relation": "calls", "confidence": "INFERRED", "source_file": "graphify-env/lib/python3.14/site-packages/jsonpickle/unpickler.py", "source_location": "L865", "weight": 0.8}, {"source": "unpickler_unpickler_restore_object", "target": "unpickler_unpickler_mkref", "relation": "calls", "confidence": "INFERRED", "source_file": "graphify-env/lib/python3.14/site-packages/jsonpickle/unpickler.py", "source_location": "L866", "weight": 0.8}, {"source": "unpickler_unpickler_restore_object", "target": "unpickler_unpickler_reset", "relation": "calls", "confidence": "INFERRED", "source_file": "graphify-env/lib/python3.14/site-packages/jsonpickle/unpickler.py", "source_location": "L868", "weight": 0.8}, {"source": "unpickler_unpickler_restore_object", "target": "unpickler_unpickler_swapref", "relation": "calls", "confidence": "INFERRED", "source_file": "graphify-env/lib/python3.14/site-packages/jsonpickle/unpickler.py", "source_location": "L869", "weight": 0.8}, {"source": "unpickler_unpickler_restore_object", "target": "unpickler_unpickler_process_missing", "relation": "calls", "confidence": "INFERRED", "source_file": "graphify-env/lib/python3.14/site-packages/jsonpickle/unpickler.py", "source_location": "L873", "weight": 0.8}, {"source": "unpickler_unpickler_restore_object", "target": "unpickler_unpickler_restore_object_instance", "relation": "calls", "confidence": "INFERRED", "source_file": "graphify-env/lib/python3.14/site-packages/jsonpickle/unpickler.py", "source_location": "L876", "weight": 0.8}, {"source": "unpickler_unpickler_restore_function", "target": "unpickler_loadclass", "relation": "calls", "confidence": "INFERRED", "source_file": "graphify-env/lib/python3.14/site-packages/jsonpickle/unpickler.py", "source_location": "L879", "weight": 0.8}, {"source": "unpickler_unpickler_restore_set", "target": "unpickler_unpickler_restore", "relation": "calls", "confidence": "INFERRED", "source_file": "graphify-env/lib/python3.14/site-packages/jsonpickle/unpickler.py", "source_location": "L883", "weight": 0.8}, {"source": "unpickler_unpickler_restore_dict", "target": "unpickler_unpickler_mkref", "relation": "calls", "confidence": "INFERRED", "source_file": "graphify-env/lib/python3.14/site-packages/jsonpickle/unpickler.py", "source_location": "L890", "weight": 0.8}, {"source": "unpickler_unpickler_restore_dict", "target": "unpickler_is_json_key", "relation": "calls", "confidence": "INFERRED", "source_file": "graphify-env/lib/python3.14/site-packages/jsonpickle/unpickler.py", "source_location": "L899", "weight": 0.8}, {"source": "unpickler_unpickler_restore_dict", "target": "unpickler_unpickler_restore", "relation": "calls", "confidence": "INFERRED", "source_file": "graphify-env/lib/python3.14/site-packages/jsonpickle/unpickler.py", "source_location": "L906", "weight": 0.8}, {"source": "unpickler_unpickler_restore_dict", "target": "unpickler_unpickler_restore_pickled_key", "relation": "calls", "confidence": "INFERRED", "source_file": "graphify-env/lib/python3.14/site-packages/jsonpickle/unpickler.py", "source_location": "L916", "weight": 0.8}, {"source": "unpickler_unpickler_restore_tuple", "target": "unpickler_unpickler_restore", "relation": "calls", "confidence": "INFERRED", "source_file": "graphify-env/lib/python3.14/site-packages/jsonpickle/unpickler.py", "source_location": "L939", "weight": 0.8}, {"source": "unpickler_rationale_27", "target": "unpickler_decode", "relation": "rationale_for", "confidence": "EXTRACTED", "source_file": "graphify-env/lib/python3.14/site-packages/jsonpickle/unpickler.py", "source_location": "L27", "weight": 1.0}, {"source": "unpickler_rationale_107", "target": "unpickler_safe_hasattr", "relation": "rationale_for", "confidence": "EXTRACTED", "source_file": "graphify-env/lib/python3.14/site-packages/jsonpickle/unpickler.py", "source_location": "L107", "weight": 1.0}, {"source": "unpickler_rationale_116", "target": "unpickler_is_json_key", "relation": "rationale_for", "confidence": "EXTRACTED", "source_file": "graphify-env/lib/python3.14/site-packages/jsonpickle/unpickler.py", "source_location": "L116", "weight": 1.0}, {"source": "unpickler_rationale_121", "target": "unpickler_proxy", "relation": "rationale_for", "confidence": "EXTRACTED", "source_file": "graphify-env/lib/python3.14/site-packages/jsonpickle/unpickler.py", "source_location": "L121", "weight": 1.0}, {"source": "unpickler_rationale_172", "target": "unpickler_obj_setattr", "relation": "rationale_for", "confidence": "EXTRACTED", "source_file": "graphify-env/lib/python3.14/site-packages/jsonpickle/unpickler.py", "source_location": "L172", "weight": 1.0}, {"source": "unpickler_rationale_177", "target": "unpickler_obj_setvalue", "relation": "rationale_for", "confidence": "EXTRACTED", "source_file": "graphify-env/lib/python3.14/site-packages/jsonpickle/unpickler.py", "source_location": "L177", "weight": 1.0}, {"source": "unpickler_rationale_182", "target": "unpickler_loadclass", "relation": "rationale_for", "confidence": "EXTRACTED", "source_file": "graphify-env/lib/python3.14/site-packages/jsonpickle/unpickler.py", "source_location": "L182", "weight": 1.0}, {"source": "unpickler_rationale_226", "target": "unpickler_has_tag", "relation": "rationale_for", "confidence": "EXTRACTED", "source_file": "graphify-env/lib/python3.14/site-packages/jsonpickle/unpickler.py", "source_location": "L226", "weight": 1.0}, {"source": "unpickler_rationale_243", "target": "unpickler_getargs", "relation": "rationale_for", "confidence": "EXTRACTED", "source_file": "graphify-env/lib/python3.14/site-packages/jsonpickle/unpickler.py", "source_location": "L243", "weight": 1.0}, {"source": "unpickler_rationale_269", "target": "unpickler_trivialclassic", "relation": "rationale_for", "confidence": "EXTRACTED", "source_file": "graphify-env/lib/python3.14/site-packages/jsonpickle/unpickler.py", "source_location": "L269", "weight": 1.0}, {"source": "unpickler_rationale_275", "target": "unpickler_make_blank_classic", "relation": "rationale_for", "confidence": "EXTRACTED", "source_file": "graphify-env/lib/python3.14/site-packages/jsonpickle/unpickler.py", "source_location": "L275", "weight": 1.0}, {"source": "unpickler_rationale_286", "target": "unpickler_loadrepr", "relation": "rationale_for", "confidence": "EXTRACTED", "source_file": "graphify-env/lib/python3.14/site-packages/jsonpickle/unpickler.py", "source_location": "L286", "weight": 1.0}, {"source": "unpickler_rationale_308", "target": "unpickler_loadmodule", "relation": "rationale_for", "confidence": "EXTRACTED", "source_file": "graphify-env/lib/python3.14/site-packages/jsonpickle/unpickler.py", "source_location": "L308", "weight": 1.0}, {"source": "unpickler_rationale_333", "target": "unpickler_has_tag_dict", "relation": "rationale_for", "confidence": "EXTRACTED", "source_file": "graphify-env/lib/python3.14/site-packages/jsonpickle/unpickler.py", "source_location": "L333", "weight": 1.0}, {"source": "unpickler_rationale_350", "target": "unpickler_passthrough", "relation": "rationale_for", "confidence": "EXTRACTED", "source_file": "graphify-env/lib/python3.14/site-packages/jsonpickle/unpickler.py", "source_location": "L350", "weight": 1.0}, {"source": "unpickler_rationale_374", "target": "unpickler_unpickler_reset", "relation": "rationale_for", "confidence": "EXTRACTED", "source_file": "graphify-env/lib/python3.14/site-packages/jsonpickle/unpickler.py", "source_location": "L374", "weight": 1.0}, {"source": "unpickler_rationale_390", "target": "unpickler_unpickler_swap_proxies", "relation": "rationale_for", "confidence": "EXTRACTED", "source_file": "graphify-env/lib/python3.14/site-packages/jsonpickle/unpickler.py", "source_location": "L390", "weight": 1.0}, {"source": "unpickler_rationale_405", "target": "unpickler_unpickler_restore", "relation": "rationale_for", "confidence": "EXTRACTED", "source_file": "graphify-env/lib/python3.14/site-packages/jsonpickle/unpickler.py", "source_location": "L405", "weight": 1.0}, {"source": "unpickler_rationale_426", "target": "unpickler_unpickler_register_classes", "relation": "rationale_for", "confidence": "EXTRACTED", "source_file": "graphify-env/lib/python3.14/site-packages/jsonpickle/unpickler.py", "source_location": "L426", "weight": 1.0}, {"source": "unpickler_rationale_458", "target": "unpickler_unpickler_refname", "relation": "rationale_for", "confidence": "EXTRACTED", "source_file": "graphify-env/lib/python3.14/site-packages/jsonpickle/unpickler.py", "source_location": "L458", "weight": 1.0}, {"source": "unpickler_rationale_525", "target": "unpickler_unpickler_restore_reduce", "relation": "rationale_for", "confidence": "EXTRACTED", "source_file": "graphify-env/lib/python3.14/site-packages/jsonpickle/unpickler.py", "source_location": "L525", "weight": 1.0}, {"source": "unpickler_rationale_647", "target": "unpickler_unpickler_restore_pickled_key", "relation": "rationale_for", "confidence": "EXTRACTED", "source_file": "graphify-env/lib/python3.14/site-packages/jsonpickle/unpickler.py", "source_location": "L647", "weight": 1.0}, {"source": "unpickler_rationale_659", "target": "unpickler_unpickler_restore_key_fn", "relation": "rationale_for", "confidence": "EXTRACTED", "source_file": "graphify-env/lib/python3.14/site-packages/jsonpickle/unpickler.py", "source_location": "L659", "weight": 1.0}, {"source": "unpickler_rationale_944", "target": "unpickler_unpickler_restore_tags", "relation": "rationale_for", "confidence": "EXTRACTED", "source_file": "graphify-env/lib/python3.14/site-packages/jsonpickle/unpickler.py", "source_location": "L944", "weight": 1.0}]}